{
  "creds": {
    "noiseKey": {
      "private": {
        "type": "Buffer",
        "data": "ML3hSsqSrre2wm+H0+JMjhG0idwbaWJZZmGNFy5lVXk="
      },
      "public": {
        "type": "Buffer",
        "data": "Y/71siT/U6TAUlkfCo47u/bUILVn6w1Xt+E/jHU8ihc="
      }
    },
    "signedIdentityKey": {
      "private": {
        "type": "Buffer",
        "data": "YFkQGfv/9VhPqQQC3QvzZELN7MZY5K5EevOF1vvY12M="
      },
      "public": {
        "type": "Buffer",
        "data": "XpQBajP7vWf3js8tz+Ii5RqiRTDDYlazbicvoSyd5D8="
      }
    },
    "signedPreKey": {
      "keyPair": {
        "private": {
          "type": "Buffer",
          "data": "8Bei5t62nAb/7BvUZcmnpiEfvFdJVFuG4DTsnQA4T0U="
        },
        "public": {
          "type": "Buffer",
          "data": "Cs4KE3YxEJ9lmaFClJxKhUk+R9Gm+SKsEc8UWhjN/S4="
        }
      },
      "signature": {
        "type": "Buffer",
        "data": "Y/VYJKQxHq1dGVhoDfJAocIKJmkmVKF2nme4cGPuvLXUITa6emsTsBxA/RKvB0+NtvxfyKc0ndVb8N4IC3xfhQ=="
      },
      "keyId": 1
    },
    "registrationId": 101,
    "advSecretKey": "bM28gVo6+NdVrKrZnfcNH/q7p20NYClyRi/D8uYb1ys=",
    "processedHistoryMessages": [
      {
        "key": {
          "remoteJid": "62859106985947@s.whatsapp.net",
          "fromMe": true,
          "id": "48C33E8FDB3D2CA26BAF1C633052448A"
        },
        "messageTimestamp": 1667846451
      },
      {
        "key": {
          "remoteJid": "62859106985947@s.whatsapp.net",
          "fromMe": true,
          "id": "4D833D9D8D5A36588E937B2C82D89E45"
        },
        "messageTimestamp": 1667846451
      },
      {
        "key": {
          "remoteJid": "62859106985947@s.whatsapp.net",
          "fromMe": true,
          "id": "28271639632D59459EC960FC9054340B"
        },
        "messageTimestamp": 1667846514
      }
    ],
    "nextPreKeyId": 36,
    "firstUnuploadedPreKeyId": 36,
    "accountSettings": {
      "unarchiveChats": false
    },
    "account": {
      "details": "CPLKgrYBEKyipZsGGAE=",
      "accountSignatureKey": "LX4PsnXtekBPH0troMYC811NvGXCEqUy9Fye/uTJtw4=",
      "accountSignature": "HaCHXlO71IsoExL0ypRjP6DA9MdNUSbycx71KG5Axxb6+T3Aps3o4dC/7927dhZtvB5jrtlADjTEhc4YJLxNAA==",
      "deviceSignature": "evyB6Fk9TFwUm1RuRN1GFA2tLWTiGBgCwqodbufVo0UrSb1QYrhYLRWlriQFXy0LftFp674A9kvtIxF0UM1EjQ=="
    },
    "me": {
      "id": "62859106985947:2@s.whatsapp.net",
      "name": "Secret Priv <3"
    },
    "signalIdentities": [
      {
        "identifier": {
          "name": "62859106985947:2@s.whatsapp.net",
          "deviceId": 0
        },
        "identifierKey": {
          "type": "Buffer",
          "data": "BS1+D7J17XpATx9La6DGAvNdTbxlwhKlMvRcnv7kybcO"
        }
      }
    ],
    "platform": "android",
    "lastAccountSyncTimestamp": 1667847258,
    "myAppStateKeyId": "AAAAAF+R"
  },
  "keys": {
    "preKeys": {
      "1": {
        "private": {
          "type": "Buffer",
          "data": "WIy2sOmZ5oO2WwWa90KhSKD8IFDfXLDFj3vWqTMW9Uo="
        },
        "public": {
          "type": "Buffer",
          "data": "U5ySSTHqra7L7rNCjDxc/3uwVE2n6rA1B2sCxARShm4="
        }
      },
      "2": {
        "private": {
          "type": "Buffer",
          "data": "uE0PbB0zlYUC+oJPHcffEbs23ScmIIKaIpq0kWAiLWs="
        },
        "public": {
          "type": "Buffer",
          "data": "RaWNY6m35ER6i7za4AY3IBbScH10+WvDlMyn+M/EEGE="
        }
      },
      "3": {
        "private": {
          "type": "Buffer",
          "data": "aP9saO+c/qm1wcdGJMQ1p5kk2CPCjYs50fJzs1einGU="
        },
        "public": {
          "type": "Buffer",
          "data": "IRpRu2WXPVTRaKzHKTQJBPOg+Upt32tPHQuV/4SzCiM="
        }
      },
      "4": {
        "private": {
          "type": "Buffer",
          "data": "aAQnIu/2RJTA1QIp4rlYrOLmYz8YbUwF9SNsMNRTFG4="
        },
        "public": {
          "type": "Buffer",
          "data": "dkPazFjHJDMO7UN281n5kugpKtpZi91pk2X+pIlyBHg="
        }
      },
      "5": {
        "private": {
          "type": "Buffer",
          "data": "+F7IHGXHUXwKtfcfNYzXYHz8LOK8j21yZyX8WQ+acV4="
        },
        "public": {
          "type": "Buffer",
          "data": "Xby5ZAqzjpA06S0bTlhPDFyipgnpcFnxGrcFBv4pzQ4="
        }
      },
      "6": {
        "private": {
          "type": "Buffer",
          "data": "4FnPC9ZnwmB5A91RERzgHoU9KVkMMpK99g2TmTav+3k="
        },
        "public": {
          "type": "Buffer",
          "data": "1pLuCQvkxj4/BZE3lB11NynjmCJ2e4vu+fWy0Og4QD8="
        }
      },
      "7": null,
      "8": {
        "private": {
          "type": "Buffer",
          "data": "CPDqeEPaj3D1Uh4pu+zJB2VIrUPvYQct51wq/tAizFQ="
        },
        "public": {
          "type": "Buffer",
          "data": "SyTXAsKupCXnmUnMtcrfBtIds1uHj0ON7zo6tait/hc="
        }
      },
      "9": {
        "private": {
          "type": "Buffer",
          "data": "oL6WOoTfWQyGJzz/ZVk4k66eb4f8+3yVq6hldwOhMV0="
        },
        "public": {
          "type": "Buffer",
          "data": "pNCD/+Rypsw3xVHzc83hCyjMIbLK+20U3DfoQDta9SU="
        }
      },
      "10": {
        "private": {
          "type": "Buffer",
          "data": "sEizV5+yn49FedBXSTmtOe7z5r0ItrBL5YeiKsiAtWU="
        },
        "public": {
          "type": "Buffer",
          "data": "P50pLoe1XO2Chl0padCcnnhgTA+aWP1Vp275rVlR1xI="
        }
      },
      "11": {
        "private": {
          "type": "Buffer",
          "data": "OMm0Ih+8YsowKHMRsTcdukNY7518jNO1u8k4/3CCh28="
        },
        "public": {
          "type": "Buffer",
          "data": "A+0uITo9F9vz/CtewJtsWv1bxjqakVf8dVwhgyydJGI="
        }
      },
      "12": {
        "private": {
          "type": "Buffer",
          "data": "mBLY8sg53yc64HLXNiUWYr+2x/ruBMLtkjGeJUXFEVs="
        },
        "public": {
          "type": "Buffer",
          "data": "4Y21K9hqwVEkBxSCzr6H5OCWUHBnag6A0TuuQuGOtWQ="
        }
      },
      "13": {
        "private": {
          "type": "Buffer",
          "data": "0Kuut+obDfmX675/la3bwwv2EI6zig4P98rx1qWdH0U="
        },
        "public": {
          "type": "Buffer",
          "data": "Atm4UyItfE0YK/nk6sf+karBnzc9NXzEUDnzpPQbBG8="
        }
      },
      "14": {
        "private": {
          "type": "Buffer",
          "data": "8ELv5ERKWHHBup7qdTZPaUSZoA2xx6GZF9KLtC4Mj0Y="
        },
        "public": {
          "type": "Buffer",
          "data": "6yayNNV5jjdF3JDff53zHpzjjbKp2iIY2hhRWSKfmT8="
        }
      },
      "15": null,
      "16": {
        "private": {
          "type": "Buffer",
          "data": "gCuLat27yn1iNGlNsiR1P7PuLYT0uwqqCXuXSqNKiWE="
        },
        "public": {
          "type": "Buffer",
          "data": "ljUB5jDDZGkk9to74Vx2QH0O5+6w89ePYIeXtznrPjk="
        }
      },
      "17": {
        "private": {
          "type": "Buffer",
          "data": "OGWEQVa63Vuv7MFI2sWYz+LuC8TPTep+c5lxFGkDeWs="
        },
        "public": {
          "type": "Buffer",
          "data": "+BTittGtqFCObq4P5vRF7QLo0ulb2cN7iD54baLpf2s="
        }
      },
      "18": null,
      "19": {
        "private": {
          "type": "Buffer",
          "data": "qOeROahF2gurgqGNU2ZCVEko6H2IB9C9fsy+SZqaxXE="
        },
        "public": {
          "type": "Buffer",
          "data": "pjQuEGZFSXAG1gvBvhCpP2jBXRIk7plowwmOxXIej1c="
        }
      },
      "20": {
        "private": {
          "type": "Buffer",
          "data": "0MT3XLuGdQC7KYWY6zGyhhYKoCsaRH3QcxWkQURp23w="
        },
        "public": {
          "type": "Buffer",
          "data": "kpKdR1ztSgEjc5A+3Ni+OyuoMHeZOuye3IARYVkcJT4="
        }
      },
      "21": {
        "private": {
          "type": "Buffer",
          "data": "sIon6z+XiR/zGQgYnFFl543CC3EmEgf80VwMYWFOgmQ="
        },
        "public": {
          "type": "Buffer",
          "data": "tg5eGO+dh4QA8EbqzTTz6xpn72WCI1WReYZn9nuarTc="
        }
      },
      "22": {
        "private": {
          "type": "Buffer",
          "data": "qNbTkyJYOhGrL+3105YC4jBVFc15hLuthRgUA81hnnk="
        },
        "public": {
          "type": "Buffer",
          "data": "aVMbn+mgXhfoehm7wXi/MOSHRhbzVJi9uiFs1giBS0M="
        }
      },
      "23": {
        "private": {
          "type": "Buffer",
          "data": "GKhzWD+uNRTSLMRiHTM/AzfT7tKkpvCjG5R0SFIRBlA="
        },
        "public": {
          "type": "Buffer",
          "data": "G1DEAeLNikhFrOJ8spj99KVqRWwCCdwSmB/LDys863U="
        }
      },
      "24": {
        "private": {
          "type": "Buffer",
          "data": "OP3Xb6o8B5YH0uRUEP9YLi0ax+Op130TzQRDwtpo3Gk="
        },
        "public": {
          "type": "Buffer",
          "data": "ZvqiBwGJSBIHImO+Jg2m+J25bS5YkQU9J712eKCuxSA="
        }
      },
      "25": null,
      "26": {
        "private": {
          "type": "Buffer",
          "data": "qF56Ko9528qwSz6ajxyXXSrx0+sO9naHObH5ZljPwl8="
        },
        "public": {
          "type": "Buffer",
          "data": "eueNyjNYy3pFHBR6QKnHLpL3P1gtTN5gL+QcWesEkyc="
        }
      },
      "27": {
        "private": {
          "type": "Buffer",
          "data": "AB/sYEFNBQLLVaIcmCBqq/O3Fbl8Ijb2hT1W3OIvMWQ="
        },
        "public": {
          "type": "Buffer",
          "data": "iPU0j2mQ76CuRZnkD8Pv7QSNwJ0wNUZ1mAFDfcqoQCU="
        }
      },
      "28": null,
      "29": {
        "private": {
          "type": "Buffer",
          "data": "SAUYcUILfjgBWRcJpf8Xv/mi+yRLm8bjq43d97SNdm0="
        },
        "public": {
          "type": "Buffer",
          "data": "1nOpqrkG2H4kIY6rf/SoZtbLQ23lNZ2xSfOFVVarKRM="
        }
      },
      "30": {
        "private": {
          "type": "Buffer",
          "data": "4GcrNpxDSF/NIPOA6uawzQc/h2V4GDtn7TbyRxUaaGI="
        },
        "public": {
          "type": "Buffer",
          "data": "bFv5R/3jcT87gqwrYwXCGa0eyOxsEMgN0Cm/E6vuPVM="
        }
      },
      "31": null,
      "32": null,
      "33": null,
      "34": {
        "private": {
          "type": "Buffer",
          "data": "6EB/w8O5rW97tZ0eanPuypQOkBP60deoqnHvg6TYZnM="
        },
        "public": {
          "type": "Buffer",
          "data": "PoZIcdWDTdZvWJQLTgdQobcexuB8B0AEiGutgU+6vwM="
        }
      },
      "35": null
    },
    "sessions": {
      "62859106985947.0": {
        "_sessions": {
          "BcaDArVv5f6fD0ZUj4aKoAsXTV4DLDyRm3RUR5HaJqNT": {
            "registrationId": 103450806,
            "currentRatchet": {
              "ephemeralKeyPair": {
                "pubKey": "BYpueSqmSZS6y1BnzeP9DKeIiTxwGL7fy3MUpqHSVa88",
                "privKey": "4KrDViRXVssNBSkZdZzQLHAifYQXyZ9eYbK7CKGuHEo="
              },
              "lastRemoteEphemeralKey": "BToiiikJC/v/2ylGQRv+NKRiZmRzldqRjHRkqVuw10Mx",
              "previousCounter": 1,
              "rootKey": "FDz+dH5rcVWUlr9JWK7mwzJhK7DmTZZLtKmUiUcv2BU="
            },
            "indexInfo": {
              "baseKey": "BcaDArVv5f6fD0ZUj4aKoAsXTV4DLDyRm3RUR5HaJqNT",
              "baseKeyType": 2,
              "closed": 1667847259946,
              "used": 1667847146502,
              "created": 1667846448966,
              "remoteIdentityKey": "BS1+D7J17XpATx9La6DGAvNdTbxlwhKlMvRcnv7kybcO"
            },
            "_chains": {
              "BT3aXXhuRpW8pztb92mAKrUGJcJCEVqRd/eQ+NJT57oH": {
                "chainKey": {
                  "counter": 7
                },
                "chainType": 2,
                "messageKeys": {}
              },
              "BSJ8Kly0qgO/DVJvx63bAYd+w9ya3RQSJcuWJBMQGqh5": {
                "chainKey": {
                  "counter": 3
                },
                "chainType": 2,
                "messageKeys": {
                  "0": "/0L6WuFVUwRBDX7/DrEUMrO9TLPimBlAGzZ+3qAdFOg="
                }
              },
              "BeqGSAqxF2xbIniFH0oeFLWsyWzTyzOLqbdE5s9YTJko": {
                "chainKey": {
                  "counter": 0
                },
                "chainType": 2,
                "messageKeys": {}
              },
              "BaTRxg2ewEx2BWatYh6d+WF4yt6lDDngVi7N/q9DprRS": {
                "chainKey": {
                  "counter": 0
                },
                "chainType": 2,
                "messageKeys": {}
              },
              "BW2ROYXNdgX8U5B2scedO+P+NSQMEXvJU3/G8QL+m9xx": {
                "chainKey": {
                  "counter": 1
                },
                "chainType": 2,
                "messageKeys": {}
              },
              "BVUkAHRQRIcJdJYTo4tnM5FBJKYkgC08d8PZ6OuXDh9W": {
                "chainKey": {
                  "counter": 0
                },
                "chainType": 2,
                "messageKeys": {}
              },
              "BYsVqCsL2cNz0wY2jBjFFrH4nojm4UXN7aqtSX0NB3oi": {
                "chainKey": {
                  "counter": 0
                },
                "chainType": 2,
                "messageKeys": {}
              },
              "BToiiikJC/v/2ylGQRv+NKRiZmRzldqRjHRkqVuw10Mx": {
                "chainKey": {
                  "counter": 0,
                  "key": "Edd9W22WhTBRJujmy/RFwJ0AaatTsurGV4wKLpm6mZQ="
                },
                "chainType": 2,
                "messageKeys": {}
              },
              "BYpueSqmSZS6y1BnzeP9DKeIiTxwGL7fy3MUpqHSVa88": {
                "chainKey": {
                  "counter": -1,
                  "key": "SmMFGuIFlalxQs+QeQ75NisuZfQ06LrFhAtEBf3TaTw="
                },
                "chainType": 1,
                "messageKeys": {}
              }
            }
          },
          "BWoi9ohpbZwQ45LQY2VgjrGlcH7jrUoLO0u3DRWBsC5L": {
            "registrationId": 103450806,
            "currentRatchet": {
              "ephemeralKeyPair": {
                "pubKey": "Beb5jMxtvijcp7A3lrGYAMWfcb4eU18wuqKpd3tF3CkO",
                "privKey": "uEdl9AzBJaH0CGFtwfTyp5tIRKmzD9KEmyHIRuELWGk="
              },
              "lastRemoteEphemeralKey": "BZnWYPp4lYrvCF1BcoSgHwO2btyZ29BM7gL0OSnkwwhn",
              "previousCounter": 1,
              "rootKey": "9BK+Uts2tNBmPFnxUyjtXMY0uB1ZrftrPACFK4uJPvE="
            },
            "indexInfo": {
              "baseKey": "BWoi9ohpbZwQ45LQY2VgjrGlcH7jrUoLO0u3DRWBsC5L",
              "baseKeyType": 2,
              "closed": -1,
              "used": 1667847411846,
              "created": 1667847259949,
              "remoteIdentityKey": "BS1+D7J17XpATx9La6DGAvNdTbxlwhKlMvRcnv7kybcO"
            },
            "_chains": {
              "BTHXpq990dNPBLd+UhdC+9j4E7RbINnM4wnC3cwWjUkl": {
                "chainKey": {
                  "counter": 0
                },
                "chainType": 2,
                "messageKeys": {}
              },
              "BdXWp+A5Z4PetP4yv6cN8gRzpCNF4gLUU1YJYtKApiQt": {
                "chainKey": {
                  "counter": 0
                },
                "chainType": 2,
                "messageKeys": {}
              },
              "BUYX986d2AQbC4APfAxq3aurfcKeJe8tqWNpzo6MD98G": {
                "chainKey": {
                  "counter": 0
                },
                "chainType": 2,
                "messageKeys": {}
              },
              "BXHC3g7+HdAMlFPd2HhHcbq2eSnV5/JRAvD6Gitp/U1J": {
                "chainKey": {
                  "counter": 0
                },
                "chainType": 2,
                "messageKeys": {}
              },
              "Bb7f8npzPCseFAIYFvVMEUVdhQqOwT6HNd4b42tc7hJa": {
                "chainKey": {
                  "counter": 0
                },
                "chainType": 2,
                "messageKeys": {}
              },
              "BYzMZEl06lgcVLQKuXd84WCtKd1/A6SwYo7VpYUOfzFA": {
                "chainKey": {
                  "counter": 0
                },
                "chainType": 2,
                "messageKeys": {}
              },
              "BZnWYPp4lYrvCF1BcoSgHwO2btyZ29BM7gL0OSnkwwhn": {
                "chainKey": {
                  "counter": 0,
                  "key": "SOwYYTSfKMTwvh/WDBuYGE1yH+00WIMVwWrCI69MC7w="
                },
                "chainType": 2,
                "messageKeys": {}
              },
              "Beb5jMxtvijcp7A3lrGYAMWfcb4eU18wuqKpd3tF3CkO": {
                "chainKey": {
                  "counter": 1,
                  "key": "W++oyqaBea8LQk9cELweudqHpaSDxA/Ztds1jlYbdTM="
                },
                "chainType": 1,
                "messageKeys": {}
              }
            }
          }
        },
        "version": "v1"
      },
      "111111.0": {
        "_sessions": {
          "BVyevAgKClWk054CndcMNFhN0M+aoIKgsTWBYrKcQdMm": {
            "registrationId": 3232002362,
            "currentRatchet": {
              "ephemeralKeyPair": {
                "pubKey": "BaPlDxWFI5NXq6SUHBK6J4pJFisRqMPkH1Ag6yZwWpZ5",
                "privKey": "oPv2S5tf38hQVic4Ptx2GIHJCxh4wBZ6PVfA9xJhP1E="
              },
              "lastRemoteEphemeralKey": "BZ+70cRMFhQJci5sw9D5ieNGjCLynzqCwoGtYjA4bUoa",
              "previousCounter": 0,
              "rootKey": "VLqxhm7XzmxacagvbVbxfPZIRb8SvFiW/8bbfbv06X8="
            },
            "indexInfo": {
              "baseKey": "BVyevAgKClWk054CndcMNFhN0M+aoIKgsTWBYrKcQdMm",
              "baseKeyType": 1,
              "closed": -1,
              "used": 1667846477138,
              "created": 1667846477138,
              "remoteIdentityKey": "BRLQZ+e9bmSkyA7TBszZTBZNF90OUrbxW6HwSUD160xm"
            },
            "_chains": {
              "BaPlDxWFI5NXq6SUHBK6J4pJFisRqMPkH1Ag6yZwWpZ5": {
                "chainKey": {
                  "counter": 15,
                  "key": "4GetkRPJcIU6p5dFTGtOqFY4/p/1KKCGK5nTQdKOIPE="
                },
                "chainType": 1,
                "messageKeys": {}
              }
            },
            "pendingPreKey": {
              "signedKeyId": 4406458,
              "baseKey": "BVyevAgKClWk054CndcMNFhN0M+aoIKgsTWBYrKcQdMm"
            }
          }
        },
        "version": "v1"
      },
      "62859106985947:3.0": {
        "_sessions": {
          "BdNXkGJsVksuBJpn5ymJV5dyFki2gsZj92snw44feAgY": {
            "registrationId": 193,
            "currentRatchet": {
              "ephemeralKeyPair": {
                "pubKey": "BQZqJLYpGbNyHANXYHpm6ilJk6gdZrb1rEbB/Ndp8uJ2",
                "privKey": "IB/F+dYpsB2TU8+sKsLBDHZNlWmKMY+PqIS5WpEj8E4="
              },
              "lastRemoteEphemeralKey": "BbHmH+dLeiVWamptBlj4EsnMTLJcSmIiAP5HzDgsDyE6",
              "previousCounter": 4,
              "rootKey": "FpIrS9vqCYU7JvjSIOAsAaClKPpggMYPgzEbaufqgMk="
            },
            "indexInfo": {
              "baseKey": "BdNXkGJsVksuBJpn5ymJV5dyFki2gsZj92snw44feAgY",
              "baseKeyType": 2,
              "closed": 1667847263871,
              "used": 1667847267209,
              "created": 1667846590830,
              "remoteIdentityKey": "BdQoMz+6J66rU35vqIeZn2v/4llY+EPb23FTXp7we0IS"
            },
            "_chains": {
              "BQiLRq+KzjGq8kg0gLhpRSlxEY+dvkiNGPEqTS6zuLxk": {
                "chainKey": {
                  "counter": 10
                },
                "chainType": 2,
                "messageKeys": {}
              },
              "Be59Ra3+pMgVIU5/rzbtZSBDSuxkei6fk/I4oUqHLhNg": {
                "chainKey": {
                  "counter": 0
                },
                "chainType": 2,
                "messageKeys": {}
              },
              "BbHmH+dLeiVWamptBlj4EsnMTLJcSmIiAP5HzDgsDyE6": {
                "chainKey": {
                  "counter": 0,
                  "key": "KuiQmHZhmOr+6AdTZMXFS075TUPdYYvQBhKL/GcZM5I="
                },
                "chainType": 2,
                "messageKeys": {}
              },
              "BQZqJLYpGbNyHANXYHpm6ilJk6gdZrb1rEbB/Ndp8uJ2": {
                "chainKey": {
                  "counter": -1,
                  "key": "0seWRoMzW9+pT/uc5i9HzPasY00uW6Fumrm5UQM44HY="
                },
                "chainType": 1,
                "messageKeys": {}
              }
            }
          },
          "BVmbn6muFu88xqqINZFD9sn/UGcH7jozDeQk0fROA11A": {
            "registrationId": 193,
            "currentRatchet": {
              "ephemeralKeyPair": {
                "pubKey": "BWOw/yiT6gTMG0Bg/G2QtSXs8UTROLajfHXiAJAvdp4o",
                "privKey": "GIIvTeTXwlkes3AXUdmjwXaGUu44l+GYhQU9EinLXks="
              },
              "lastRemoteEphemeralKey": "BbHmH+dLeiVWamptBlj4EsnMTLJcSmIiAP5HzDgsDyE6",
              "previousCounter": -1,
              "rootKey": "soqDu6pqD+YHvI3YXBY5omqXmzBUmnuKZCEc5vY0evw="
            },
            "indexInfo": {
              "baseKey": "BVmbn6muFu88xqqINZFD9sn/UGcH7jozDeQk0fROA11A",
              "baseKeyType": 1,
              "closed": 1667847265041,
              "used": 1667847263871,
              "created": 1667847263871,
              "remoteIdentityKey": "BdQoMz+6J66rU35vqIeZn2v/4llY+EPb23FTXp7we0IS"
            },
            "_chains": {
              "BbHmH+dLeiVWamptBlj4EsnMTLJcSmIiAP5HzDgsDyE6": {
                "chainKey": {
                  "counter": 0,
                  "key": "TIClAwQJsTaRmzo2oKCyNUDHI3ha65BM4kma+bj7pdU="
                },
                "chainType": 2,
                "messageKeys": {}
              },
              "BWOw/yiT6gTMG0Bg/G2QtSXs8UTROLajfHXiAJAvdp4o": {
                "chainKey": {
                  "counter": -1,
                  "key": "P9rKkLO88dOL0KLaTVEEL+yP8HsZyCrvJhryZSsqd4E="
                },
                "chainType": 1,
                "messageKeys": {}
              }
            },
            "pendingPreKey": {
              "signedKeyId": 1,
              "baseKey": "BVmbn6muFu88xqqINZFD9sn/UGcH7jozDeQk0fROA11A",
              "preKeyId": 16
            }
          },
          "BR82Xg1ZPOkb1Hfr/lyPohUgo0Qqa8tOKVfTVOUM3YgL": {
            "registrationId": 193,
            "currentRatchet": {
              "ephemeralKeyPair": {
                "pubKey": "BbPtJHy3yjveYLzheBLkgvS7oQFXbVWHIDTNtyFhOuVk",
                "privKey": "+NJqYThGr0/wu0UtQGyGcfIIrHTRVpxxYZ5EG6c1H28="
              },
              "lastRemoteEphemeralKey": "BbHmH+dLeiVWamptBlj4EsnMTLJcSmIiAP5HzDgsDyE6",
              "previousCounter": -1,
              "rootKey": "0iZdUYo7kwCHHxuHm+60fHHhA5Tpegh4/RNPEdlTqCU="
            },
            "indexInfo": {
              "baseKey": "BR82Xg1ZPOkb1Hfr/lyPohUgo0Qqa8tOKVfTVOUM3YgL",
              "baseKeyType": 1,
              "closed": 1667847268975,
              "used": 1667847265041,
              "created": 1667847265041,
              "remoteIdentityKey": "BdQoMz+6J66rU35vqIeZn2v/4llY+EPb23FTXp7we0IS"
            },
            "_chains": {
              "BbHmH+dLeiVWamptBlj4EsnMTLJcSmIiAP5HzDgsDyE6": {
                "chainKey": {
                  "counter": 0,
                  "key": "8M9W/pjH7NWgNLxN21WEFwmUqyq2zvGRn7MsMaX8k6s="
                },
                "chainType": 2,
                "messageKeys": {}
              },
              "BbPtJHy3yjveYLzheBLkgvS7oQFXbVWHIDTNtyFhOuVk": {
                "chainKey": {
                  "counter": 0,
                  "key": "Fp0lGYA+8iDIDWG1UMrUBHMKxJl3mcaOOEq3nAJ4GwM="
                },
                "chainType": 1,
                "messageKeys": {}
              }
            },
            "pendingPreKey": {
              "signedKeyId": 1,
              "baseKey": "BR82Xg1ZPOkb1Hfr/lyPohUgo0Qqa8tOKVfTVOUM3YgL",
              "preKeyId": 12
            }
          },
          "BVDqAFFHMc9n/6j5urFrs181IrCZxoMmtJ45/9Rop1p1": {
            "registrationId": 193,
            "currentRatchet": {
              "ephemeralKeyPair": {
                "pubKey": "BfM1dEWaugzhjwi0c7jYSvb/FdYk9y0xzSwbr76SK5MC",
                "privKey": "YGl7PMeWG+Hd5LtmNMdvwiIE/hbKIbp1ZxusRWK8kmo="
              },
              "lastRemoteEphemeralKey": "BZzLGDFEDAuuMHRcLrF++TyXW/eIafX4UU+7Tcmvcwo7",
              "previousCounter": 0,
              "rootKey": "jVLEHzVcZoQoZL9WC+jFLIr4XGDyFtdMK4S6QmbAk10="
            },
            "indexInfo": {
              "baseKey": "BVDqAFFHMc9n/6j5urFrs181IrCZxoMmtJ45/9Rop1p1",
              "baseKeyType": 1,
              "closed": -1,
              "used": 1667847326376,
              "created": 1667847268974,
              "remoteIdentityKey": "BdQoMz+6J66rU35vqIeZn2v/4llY+EPb23FTXp7we0IS"
            },
            "_chains": {
              "Bb5GpE0rcraI05Ai8y0DyoCa55jzmnHNL5KObyEOzb1X": {
                "chainKey": {
                  "counter": 0
                },
                "chainType": 2,
                "messageKeys": {}
              },
              "BZzLGDFEDAuuMHRcLrF++TyXW/eIafX4UU+7Tcmvcwo7": {
                "chainKey": {
                  "counter": 0,
                  "key": "mEvhuDn+en6M5TI56ZuFKjR6pdB7c8oFNb5Wy9WGu0s="
                },
                "chainType": 2,
                "messageKeys": {}
              },
              "BfM1dEWaugzhjwi0c7jYSvb/FdYk9y0xzSwbr76SK5MC": {
                "chainKey": {
                  "counter": 4,
                  "key": "jUBfYzdNVZGK7zjDckr14ioW9p/2sYC6+qzhsijKcfA="
                },
                "chainType": 1,
                "messageKeys": {}
              }
            }
          }
        },
        "version": "v1"
      },
      "6285155342344.0": {
        "_sessions": {
          "BSPXPVwj8L7v9oTEv1noj6fNNKVU0vnHx6bndsUMyyp3": {
            "registrationId": 448517049,
            "currentRatchet": {
              "ephemeralKeyPair": {
                "pubKey": "BaC4YZz/2i50WdtMpeeBk3FZUkQ7XvSA8IvNiZz+dFxL",
                "privKey": "qCSCtzXHy2OazVn2fvL3mlozqQ2OtKbRwCnRFRhe6mY="
              },
              "lastRemoteEphemeralKey": "BatSjE1d1xYThW73VHhlYYZij1GqZBuurhhV7+q9On58",
              "previousCounter": 0,
              "rootKey": "PaWwX2PksqvnL2wzmqx7yTMRvXNbu/qdZmXwFBLizdw="
            },
            "indexInfo": {
              "baseKey": "BSPXPVwj8L7v9oTEv1noj6fNNKVU0vnHx6bndsUMyyp3",
              "baseKeyType": 2,
              "closed": 1667846958763,
              "used": 1667846621647,
              "created": 1667846621647,
              "remoteIdentityKey": "BfanoVEPCbE1oYzhMjDDxPkdi0b9gvbH/ua91Axa9rxj"
            },
            "_chains": {
              "BatSjE1d1xYThW73VHhlYYZij1GqZBuurhhV7+q9On58": {
                "chainKey": {
                  "counter": 6,
                  "key": "whTDP6ggfrvPQOiMWPJBg+curVGwmAjXYYSkhSAl8QE="
                },
                "chainType": 2,
                "messageKeys": {
                  "5": "8JAQ+TcGfGSmQcQrchNxL1GgSyPS7t8v5hIU07PZ60k="
                }
              },
              "BaC4YZz/2i50WdtMpeeBk3FZUkQ7XvSA8IvNiZz+dFxL": {
                "chainKey": {
                  "counter": -1,
                  "key": "GnWy/SQEsyTxbWPiwcIO1ju2Hqea/lUYqpaFIGwdNmc="
                },
                "chainType": 1,
                "messageKeys": {}
              }
            }
          },
          "BQZRYtbLE/M3cozzcgoUJNji0e7mF+M4XdX9FwH3MvZR": {
            "registrationId": 448517049,
            "currentRatchet": {
              "ephemeralKeyPair": {
                "pubKey": "BU3oESwTbRiXG6iHo0/0o/idjvJz7l3i/v3RhmDdFz8b",
                "privKey": "yIo/fQAnc+Uro0Iobicl5LqE9xQzcNvGa2V64ZzvSGM="
              },
              "lastRemoteEphemeralKey": "BUxUx4fEr8orGAAlXCcq9kzURWNDHEzVt1qqUL/OyvE7",
              "previousCounter": 0,
              "rootKey": "DHmS0aOo/IBUChTB1x/9FOS9xzlQ/pCzSaDJQaH7kAQ="
            },
            "indexInfo": {
              "baseKey": "BQZRYtbLE/M3cozzcgoUJNji0e7mF+M4XdX9FwH3MvZR",
              "baseKeyType": 2,
              "closed": 1667846961956,
              "used": 1667846958765,
              "created": 1667846958765,
              "remoteIdentityKey": "BfanoVEPCbE1oYzhMjDDxPkdi0b9gvbH/ua91Axa9rxj"
            },
            "_chains": {
              "BUxUx4fEr8orGAAlXCcq9kzURWNDHEzVt1qqUL/OyvE7": {
                "chainKey": {
                  "counter": 0,
                  "key": "oYD4J6lpHczWt9fMxfDDDLRLxH7zu/WF5gwpZUqU3Fw="
                },
                "chainType": 2,
                "messageKeys": {}
              },
              "BU3oESwTbRiXG6iHo0/0o/idjvJz7l3i/v3RhmDdFz8b": {
                "chainKey": {
                  "counter": -1,
                  "key": "jUJRPXcOVLMYswZ2Jn3lT1roe7ODHIekFD5nbolD0SM="
                },
                "chainType": 1,
                "messageKeys": {}
              }
            }
          },
          "BXYORqcmMrio2cEQ6GEoQJd8Af0OPaKtNSkWUGcQJEkZ": {
            "registrationId": 448517049,
            "currentRatchet": {
              "ephemeralKeyPair": {
                "pubKey": "BcMxvocEbZvFX19Ft6PynN/6JRv3fXwYUfrDrDVoQrhm",
                "privKey": "kA+wYQO/zRuSC8bOd8Pvs+kY3omjucjpInlVPKhJA10="
              },
              "lastRemoteEphemeralKey": "Bbh3F3MZu/uB27ptRxmR67UkGPDMVId9fCZFUt/IVHwC",
              "previousCounter": 0,
              "rootKey": "HpKabZKX7Muz0Oo4QlSkdHpn7xYAJq0PotkqDbTvHQ0="
            },
            "indexInfo": {
              "baseKey": "BXYORqcmMrio2cEQ6GEoQJd8Af0OPaKtNSkWUGcQJEkZ",
              "baseKeyType": 2,
              "closed": 1667846965245,
              "used": 1667846961957,
              "created": 1667846961957,
              "remoteIdentityKey": "BfanoVEPCbE1oYzhMjDDxPkdi0b9gvbH/ua91Axa9rxj"
            },
            "_chains": {
              "Bbh3F3MZu/uB27ptRxmR67UkGPDMVId9fCZFUt/IVHwC": {
                "chainKey": {
                  "counter": 0,
                  "key": "Ni2sMUJuAL5uN5SS10ArgFvP7Yc5JnDF9eo1+syJ6fE="
                },
                "chainType": 2,
                "messageKeys": {}
              },
              "BcMxvocEbZvFX19Ft6PynN/6JRv3fXwYUfrDrDVoQrhm": {
                "chainKey": {
                  "counter": -1,
                  "key": "l+7E/3tKJr+qTTdQ+yfm//9t8GTDSRZxv+TtHD6jYzg="
                },
                "chainType": 1,
                "messageKeys": {}
              }
            }
          },
          "BbaIYkDqtmww+lQNtWJ/l8oHjpXifZmiyzlBqHuk37x9": {
            "registrationId": 448517049,
            "currentRatchet": {
              "ephemeralKeyPair": {
                "pubKey": "BWDLy1JdCw1nk5DsKPwoBA1M5isvCWk0yA3bp+6kG50H",
                "privKey": "uCCWaMM4kIEruDWDIjyQ9zkwVvawxcP59K2ZtBZaQWE="
              },
              "lastRemoteEphemeralKey": "BcR5xvnXgHSWfpJmPmkjer3NnymKT+5uMwT17vkJPHFq",
              "previousCounter": 0,
              "rootKey": "R7arB9vxV+uOOsuGrKDJLTws0hCOt2xNk6BW/PW5T0A="
            },
            "indexInfo": {
              "baseKey": "BbaIYkDqtmww+lQNtWJ/l8oHjpXifZmiyzlBqHuk37x9",
              "baseKeyType": 2,
              "closed": -1,
              "used": 1667846965247,
              "created": 1667846965247,
              "remoteIdentityKey": "BfanoVEPCbE1oYzhMjDDxPkdi0b9gvbH/ua91Axa9rxj"
            },
            "_chains": {
              "BcR5xvnXgHSWfpJmPmkjer3NnymKT+5uMwT17vkJPHFq": {
                "chainKey": {
                  "counter": 7,
                  "key": "+3yev77eIm8Lm4+K8OkIaMaS9OeMQNAcL64VfJUh8H8="
                },
                "chainType": 2,
                "messageKeys": {
                  "2": "raTPQRX2xOf4tl3PczV74pMwhUHkdUmvBgP43BxnUJ8=",
                  "4": "V5Nr52r3yjqQ5+LTQ6ohmTLKEu6zgoJN5pzBfaJpTP8="
                }
              },
              "BWDLy1JdCw1nk5DsKPwoBA1M5isvCWk0yA3bp+6kG50H": {
                "chainKey": {
                  "counter": 3,
                  "key": "AvwLKwsUNdBlQgh2NtqgUkyJuJT+OGKSL3V1ZS2huYc="
                },
                "chainType": 1,
                "messageKeys": {}
              }
            }
          }
        },
        "version": "v1"
      },
      "6281996224181.0": {
        "_sessions": {
          "BRUfxxZLmiD71LftCcLeo1MqnzG5HREc6tY58RnHWFIN": {
            "registrationId": 1521853831,
            "currentRatchet": {
              "ephemeralKeyPair": {
                "pubKey": "BePZ9QhhyB6++4MuSEe3ig0Z0xRZGUnIkyh88RZSIyUi",
                "privKey": "YCuP2pWUHLTycUivQ40j0S0iG6tOsrFH9Ph4kvgcl1g="
              },
              "lastRemoteEphemeralKey": "BfCnp96JiF6Xaf5nGKeReqEDHsForyAr6laKWwOVoP91",
              "previousCounter": 0,
              "rootKey": "BzNpU9TPvdgxc7nP/sNSNPA6Z99tLXPx5rxKl1+GKw0="
            },
            "indexInfo": {
              "baseKey": "BRUfxxZLmiD71LftCcLeo1MqnzG5HREc6tY58RnHWFIN",
              "baseKeyType": 2,
              "closed": -1,
              "used": 1667847078268,
              "created": 1667847078268,
              "remoteIdentityKey": "BT+2wv16GpaHAIx/UOwDfp68FSaQHt9yaEqqRvqSJCMW"
            },
            "_chains": {
              "BfCnp96JiF6Xaf5nGKeReqEDHsForyAr6laKWwOVoP91": {
                "chainKey": {
                  "counter": 0,
                  "key": "4lg6kuBtLl8PNOaHU1wgALwHXaOepFGH/egBQX9O5hA="
                },
                "chainType": 2,
                "messageKeys": {}
              },
              "BePZ9QhhyB6++4MuSEe3ig0Z0xRZGUnIkyh88RZSIyUi": {
                "chainKey": {
                  "counter": -1,
                  "key": "6iGXSxgf+4R7cs90a8E6ONrL477Wd5EG3bnznUd+Xyo="
                },
                "chainType": 1,
                "messageKeys": {}
              }
            }
          }
        },
        "version": "v1"
      },
      "6281221719733.0": {
        "_sessions": {
          "BWFabikj+/rWispcCCIPur3ELD2c9k+JnQ4V+8A14G1V": {
            "registrationId": 183305158,
            "currentRatchet": {
              "ephemeralKeyPair": {
                "pubKey": "BURwLqi9youimTBGwhBSx0+CpWWjYQ9PEP5iHVzm4C0j",
                "privKey": "UB6khdLc1WHlTZdCJF+2Uhurts4IblzLtAoIHqGd7VI="
              },
              "lastRemoteEphemeralKey": "BQx/1KMHUqmgKGNJ7iv0pXOp4fxOcG8JCVarM3CKNXUc",
              "previousCounter": 0,
              "rootKey": "tX74hq9Sbk0UuhMM8rYfeLxiI0DtKBBwbltuaNKdCko="
            },
            "indexInfo": {
              "baseKey": "BWFabikj+/rWispcCCIPur3ELD2c9k+JnQ4V+8A14G1V",
              "baseKeyType": 2,
              "closed": -1,
              "used": 1667847394756,
              "created": 1667847394756,
              "remoteIdentityKey": "BbLCOh8DZnNY9G15x5jVcR9Vixx82qNpJl6X1Fe+IoM/"
            },
            "_chains": {
              "BQx/1KMHUqmgKGNJ7iv0pXOp4fxOcG8JCVarM3CKNXUc": {
                "chainKey": {
                  "counter": 0,
                  "key": "U+xXo8OyfSgJw13GpZnGb2K2IcqbblSAeA217bWkgzU="
                },
                "chainType": 2,
                "messageKeys": {}
              },
              "BURwLqi9youimTBGwhBSx0+CpWWjYQ9PEP5iHVzm4C0j": {
                "chainKey": {
                  "counter": -1,
                  "key": "235eFZeVKyrNk2aS7kYdSfNHthvrDBGQifseLc6affo="
                },
                "chainType": 1,
                "messageKeys": {}
              }
            }
          }
        },
        "version": "v1"
      },
      "6285722029127.0": {
        "_sessions": {
          "BfI8rUlPIRXL0m0nWr1zZbna+pMSc/JtEp8X4usOb31E": {
            "registrationId": 53698295,
            "currentRatchet": {
              "ephemeralKeyPair": {
                "pubKey": "BRojS/GU9f3vB+9Ikkd0KrKVfXb1q+wCwxtO2a4mWAQn",
                "privKey": "qOs7Hzn555uCzVtKNo8XR93HSWIamTqP01T/4dX4Q3Y="
              },
              "lastRemoteEphemeralKey": "BYRBazFPfSMOEiZqTjzu0vsk93/XeNxto9Zr6JcmAlwh",
              "previousCounter": 0,
              "rootKey": "ixn+vfaN17YfNOvVjO3RZqs9SVSx+CMjZeIGgpI2zcs="
            },
            "indexInfo": {
              "baseKey": "BfI8rUlPIRXL0m0nWr1zZbna+pMSc/JtEp8X4usOb31E",
              "baseKeyType": 2,
              "closed": -1,
              "used": 1667847407314,
              "created": 1667847407314,
              "remoteIdentityKey": "Ba0lhODdr8qJjcGCk29Xx0MOIYjfym8UzdGAPlWGMwU4"
            },
            "_chains": {
              "BYRBazFPfSMOEiZqTjzu0vsk93/XeNxto9Zr6JcmAlwh": {
                "chainKey": {
                  "counter": 0,
                  "key": "G+qU8+RkMiHeskJiXl8/kmibrlADEM74kZUmLWny2kE="
                },
                "chainType": 2,
                "messageKeys": {}
              },
              "BRojS/GU9f3vB+9Ikkd0KrKVfXb1q+wCwxtO2a4mWAQn": {
                "chainKey": {
                  "counter": -1,
                  "key": "dwBMfM3+m7ACE268g7OCQxCcQkEev6vFu+V3o0PkcFE="
                },
                "chainType": 1,
                "messageKeys": {}
              }
            }
          }
        },
        "version": "v1"
      }
    },
    "appStateSyncKeys": {
      "AAAAAF+R": {
        "keyData": "g4eZDmfHMxuFxeHYlTCq6dZQrfl+uWVcXucjIW77HSs=",
        "fingerprint": {
          "rawId": 381724018,
          "currentIndex": 1,
          "deviceIndexes": [
            0,
            1
          ]
        },
        "timestamp": "1667846449399"
      }
    },
    "appStateVersions": {
      "critical_block": {
        "version": 1,
        "hash": {
          "type": "Buffer",
          "data": "+NKRua4hM4hjojYgkvPUBcXmesKp/R8SzRH6LQGPy9go2WNzsc5WB6NVO/sbe7Z6LkPKnl2KcDo+Zlc0dRMInjFE6SIMO87B9kHilx5v2ngsf9wZtKiehXZwGFNWhzDCkXGy+dckdsTj/OG+OG557YuIdhUo5pdj5/zu1hZimwk="
        },
        "indexValueMap": {
          "YWNlEYPJWRYO97XYWYr7nhsjFpNp8WVMh0/I0Iedm/Y=": {
            "valueMac": {
              "type": "Buffer",
              "data": "o2Gpg6+dpHjtktWiC62waPQ1hvoxmXi4ZzNv9pnhoHc="
            }
          },
          "f9v3m3tp3AI3cmNT1BVYV/98kEihGHzbpd1xENTw35I=": {
            "valueMac": {
              "type": "Buffer",
              "data": "1zPtp4VAOhs92vEpG40HiIAMCxm+Vbz68Qw/2d/Rq50="
            }
          }
        }
      },
      "regular": {
        "version": 1,
        "hash": {
          "type": "Buffer",
          "data": "/GKkeqm03VK7T5bn5Li2F3ZZcGuEeG1e9UtSO3fVJssOG1YFVQt69BVoUoeejmGJahvo58CKOhYvmu5W7Ga61ba7BP7FzarcHfdzn2/sXWIUiSSqpNNThMwz1dkBHW6U+71G9NAP2QNE7hvOpjIFHeDvqSi7cU05hoLos6eA6b4="
        },
        "indexValueMap": {
          "bz2vAKw1hpNBwlUXAHbqX/acl/V3YY5MgzXgW3gzt+Q=": {
            "valueMac": {
              "type": "Buffer",
              "data": "f/3y5umonaTLS3ehGH03eYtbom52CZC1z6bOkYaIz1I="
            }
          }
        }
      },
      "critical_unblock_low": {
        "version": 1,
        "hash": {
          "type": "Buffer",
          "data": "BeZkHTwTOOASTp7VS78dmlMvF1lNNrtlmNC9S4TMBCbDCikT3vviM4PRuvf12s9iPSCDKo5zCAE/aOzRs0E7BEArR2gUJLyJr4CEE6j4rE4BQQbq2+f2y4elCVnu5ZnDUGDfmiq8apmkaFFupKFGU/O9Y6Q9dblstd/YO2l4jBQ="
        },
        "indexValueMap": {
          "avRpijlEvCAT32cuOG9axKmJXrUwirIC1YSZsal2SqY=": {
            "valueMac": {
              "type": "Buffer",
              "data": "5eeEWhGfv3EnTy0caDUDYcCdDt/j3Fmx+CRiN8eb/gY="
            }
          },
          "2dmUxZ7yZwP0NUwvhgbkntY6HThBlXJvl0mAau8xMds=": {
            "valueMac": {
              "type": "Buffer",
              "data": "90t460tNCkMTf1woAFjvPkgCw1NbXJT1gXvu6eLel78="
            }
          },
          "5kaChm9R9qpkxjd+WViOQNSN7hlVcRR9LGM/rlaXD9c=": {
            "valueMac": {
              "type": "Buffer",
              "data": "HXN+kg+TS18rZsL2FMBaL5ivA1Ii7gFKEcQ7iyN42SU="
            }
          },
          "yBkcXi2vBx9KEMpePw0kUE/BCa3LnOb2nmTI9cteyQ4=": {
            "valueMac": {
              "type": "Buffer",
              "data": "ykkXQGQPHj2WNtoIy9/3rpAtBoN4iu1ioVd6HJ3nLRo="
            }
          },
          "sBtrNcZzVQyeblMRWcRtq0r2opuYMQqMWXeK7adIIl8=": {
            "valueMac": {
              "type": "Buffer",
              "data": "KqEBG3r77Xs9MRUyBr5lHzltiKlK/S29XyAkbka/trE="
            }
          },
          "Z51Vj4Kwk55d6R5nu0igkufxUYuKLQeoF4ov9rkv7yc=": {
            "valueMac": {
              "type": "Buffer",
              "data": "WraLOKaszCPMlfQJtEN5EMk0Xh30QaltXJBcqkqRea0="
            }
          },
          "/VHt3weO5a6UYkJeuEJ90minH5K5U9jB6TmW5ecqG+4=": {
            "valueMac": {
              "type": "Buffer",
              "data": "EVTZFQPQMMC2LAPTARHZdTKB/tkAFPTZn13T6NWDmvo="
            }
          },
          "V6I8skIeTjoS3NYr96FfWqmrlmiANurtVfc7rgeG2zA=": {
            "valueMac": {
              "type": "Buffer",
              "data": "23U4d+YRTWe2OB4XX8rpD++ET6nzpXbH4rBdxrl1Jq4="
            }
          },
          "W53/1GIyxxDz4yI1xTExXGC8Kq+K++TygwboZA08OVo=": {
            "valueMac": {
              "type": "Buffer",
              "data": "GlL15j4fEtPNzxMaz23mQnJm6L5Wq4nPChDx/I0S30E="
            }
          },
          "UhK7J367A5oOyd0H19lU/bu704ssnx2bZ59yyd1Q+Vs=": {
            "valueMac": {
              "type": "Buffer",
              "data": "xI84kBkVXLk5xZBoDMZoSc7/JiCGZdga2H2geKvL93Q="
            }
          },
          "rTXuic7EdmSbIF2Ej4z9h/fiYW39VcnZcrQfwxfIcQQ=": {
            "valueMac": {
              "type": "Buffer",
              "data": "tRywenU1Xs7TdxlvQdzb05842Si7xlSlcyWqiDLhYi0="
            }
          },
          "PhL4WY5ns3iyYxRCStNsYBqFxC7mSYJSyRLwDepgzYY=": {
            "valueMac": {
              "type": "Buffer",
              "data": "4wTbclGoUB37kzrUydzU735G+cz4pTheDQsZlEctm24="
            }
          },
          "DayVAsMlAicCYb/TZPkGqcofRWS5zA9wl0HqgcZ5CQA=": {
            "valueMac": {
              "type": "Buffer",
              "data": "jeXuYBQiUfxyWAyiuGs+DchmxSeF4B5OdReK9anlvnQ="
            }
          },
          "pGvbVIxhMHgoOLe4kf4DtLMyY6wjAfwuij6XEx9l8Z8=": {
            "valueMac": {
              "type": "Buffer",
              "data": "X3nsXXGQ0GdJmsqiMGqdojqVVyY3Zz4WWo6gP36WvjE="
            }
          },
          "W3jBT5EoucnI70p1HFJSFBuExP7Du0+1UXawXcjOSIs=": {
            "valueMac": {
              "type": "Buffer",
              "data": "nKl9vsyt2jiBRcp8MtJmW6xS4iEJBVxb4+kHB+GO3hc="
            }
          },
          "zCqYfW207lKgV7B5EkzynPMa2r5GyErXKp/3iBMLjnM=": {
            "valueMac": {
              "type": "Buffer",
              "data": "s9dcFmjwUB8c+zLUgsyBuwX7xUY4jemsAlsnZlrV5c8="
            }
          },
          "n+uN3KzCXOThwy5M+AzT9KeMly6ozvuWcUhQyVtENII=": {
            "valueMac": {
              "type": "Buffer",
              "data": "ryAljMzX9JZUSczWd/QJ+9dh019vV28DGVlSP+VAszc="
            }
          },
          "gyJrKsuHjMuDfnxaGheQ8cdFFMiDcmOBoOEleobHcaE=": {
            "valueMac": {
              "type": "Buffer",
              "data": "kkhfPPvB6H/qVclZRc/v2nhcCXMA7cR6gOkHPjnMNsI="
            }
          },
          "7PTTPuucDixsfglPsQe0cnrhqVojsXinpIZ0deTNN3c=": {
            "valueMac": {
              "type": "Buffer",
              "data": "MuDZug/haEsJgFRms5w1ZCcsHEEFCK/f+ix5LemTOlw="
            }
          },
          "FQe7o0D7syjnFvxXbnCeuaOXOK1K3BtXjjt7jIgaTJg=": {
            "valueMac": {
              "type": "Buffer",
              "data": "vrAdhYlZOc0AkJieZQ5I9QvDS5TiygJCc0appCpBFpE="
            }
          },
          "liW0qvRnltWAOW8ay3Sv4Q9iJNB7qKJYWsMYaa8iTnc=": {
            "valueMac": {
              "type": "Buffer",
              "data": "UnsULxwaCNVTGncKlPbviLSaV7Cyfsryg3yGIpKhTg0="
            }
          },
          "8GiFFdZzyj+wEQR8HiO5lxYGGOTQbBVnpwpJQJ/G/qY=": {
            "valueMac": {
              "type": "Buffer",
              "data": "wTBXpQG/O897Gj3gjNh3ktu95vBrgl+MaDNbZeTqWW4="
            }
          },
          "Pcd9+63Eooho4SghxHRHpji8kNfqdgz8AeNEkdWVilc=": {
            "valueMac": {
              "type": "Buffer",
              "data": "c7mqMPnt4FN7uZtqPzMtgVkSpFW5WxuWNpg0ZXE7cd8="
            }
          },
          "awcRrou6BHLaOHPaj7AAYLRFeQgDEAx98GO9Z6458pw=": {
            "valueMac": {
              "type": "Buffer",
              "data": "+SDQvzXN+au6jFHzGr5Sc7Bl2KHfVMJI7Rv+Lvs//no="
            }
          },
          "K5fHwh8OGCJCHwQ2nr5TMXmyGuZn7uHewMmfS6gcpgo=": {
            "valueMac": {
              "type": "Buffer",
              "data": "99Or0OTwqrAbQd/iUPRh7pImcvfzesSqQQLAGS7P18o="
            }
          },
          "yeHwATkBH4JRkhSb8+3AHfHd1BLQTEwZNY59NsSxCXo=": {
            "valueMac": {
              "type": "Buffer",
              "data": "FznFlUyedG620qIbJwd/CHFw+Zu+1yNbtXJN6a5qWYE="
            }
          },
          "RifvHoWBKZPJ4lThwip4Gz6NYxI/yQYVAP7IOgPgSLY=": {
            "valueMac": {
              "type": "Buffer",
              "data": "YC070JHQ6I3VV+khswWdLuCUwUpoiyIbgSYki48T+DM="
            }
          },
          "GUziOPeEQo778PtJ545x1Ms3oNa5I6hoBb8pWe4lzHE=": {
            "valueMac": {
              "type": "Buffer",
              "data": "eRmuz+HTrnlVNLAqV8pGG2dCBdfGQulG/DKsRJqA3aM="
            }
          },
          "TxwOMUsEZCNgazldVxn5TYYDKllOd7tP9Mpo7MedGXc=": {
            "valueMac": {
              "type": "Buffer",
              "data": "Tx6ks1PnwLm+isoadaCsUxtfo/zCbA6x9OITtsEaBZ4="
            }
          },
          "zPzFh8Sez59ott1Liiab1J9B6j56+zwnYq9EfVGTfQI=": {
            "valueMac": {
              "type": "Buffer",
              "data": "2b/UHPhXYB650iddtM0YOoBqV3GKTDbOuptpbrG4+jo="
            }
          },
          "ehEejmrKvb24k9+t1GYFXFrLC8TV0zGniZw3/JCQCpM=": {
            "valueMac": {
              "type": "Buffer",
              "data": "hTE3bgwDuMvxYvNOgwtbWZX4+aKfZ6nYFz1sbF3H7Nw="
            }
          },
          "KYOJ3PZaP4nXBP7nDi04nUJMmOQsszaNbzl9mQnuEic=": {
            "valueMac": {
              "type": "Buffer",
              "data": "cMXeKAC717jAE5ogvHgkiugRCSgmPr6LcXlr3t0VOe8="
            }
          },
          "E8zJhufZvfu2KfN0zN2eX8pOKX2cmIftyfXDfZC0HX0=": {
            "valueMac": {
              "type": "Buffer",
              "data": "lcEpzNEWSj2onwt6+ze+d9F1aU4hx8YHC4LBpR3lblc="
            }
          },
          "PVrWJwqCAd8uqN7u0e6cbxdj5cHBmzHB9pSL+KgBf7w=": {
            "valueMac": {
              "type": "Buffer",
              "data": "0qtkfcz4vPAQYxdoSKkQzJfD4oBU3TXSSQgDEKUX19s="
            }
          },
          "dP2fuNoKdt501EFuJh8R43s0qqzhQyWd7C1BlohWGkE=": {
            "valueMac": {
              "type": "Buffer",
              "data": "FkXesZzTt6pPTldpUYLWQEGyEpG22+5JPPVsk/RvcEI="
            }
          },
          "yUXRprlZzTLy5F8vRNftGHO9QI5u5GWhCIOYy8jWtbM=": {
            "valueMac": {
              "type": "Buffer",
              "data": "0S8EpvCRm0Uo3vEFkCqzKFz0XYx5ByWbx5l4opext2M="
            }
          },
          "evU29HFvu4Hnth4yoAQS2NQVKZDKwpR9NlIFFlDD3uw=": {
            "valueMac": {
              "type": "Buffer",
              "data": "cXtBCgoVHGrQEjlOd+r5YfSH9cBujIdf9Qy32mV3NFg="
            }
          },
          "N9n5fqxEKFcjD68ceLZc8BT6jSr5+AdZP291j3YaHjQ=": {
            "valueMac": {
              "type": "Buffer",
              "data": "rueh/XejIvexHdG7zwwy0nNv9HqqBXZisfVnAhuqs3Y="
            }
          },
          "sENqAaGiebfQA8XvBICA+oyWA4xt+avJn99lpL4BLoQ=": {
            "valueMac": {
              "type": "Buffer",
              "data": "/lMIyCavBPM5YldU+dnrCPeao3pHfCJ6dXG5DS6kHIA="
            }
          },
          "aSVprrcOl8DGWjlxtlUb1i2hUPC2hxrY96fy6P8ePCs=": {
            "valueMac": {
              "type": "Buffer",
              "data": "JbAeT+YS8aDIE5MENYiGLgp3bxfhG8RBSVJg6o1sgrU="
            }
          },
          "AKgSB0MnBui/HY8W93nfLjwwaZ1ToBJ7RcxZ1KK8Q9w=": {
            "valueMac": {
              "type": "Buffer",
              "data": "SaEJwd+HiOCWQWLSIY1fS8mu8+9AvOzpA2Iz3T8kuxI="
            }
          },
          "HRi0RlEvk4HGGE/XtoWTs3u57NihZCApWELX1eB0+3E=": {
            "valueMac": {
              "type": "Buffer",
              "data": "rvs6HaCKIbJNg0ZJtOfVpuWyPj1O3eRFh103EC64Avk="
            }
          },
          "85gEqzngMsahUDGLAnzZcqyka/Cn5VTN631uhkZGEts=": {
            "valueMac": {
              "type": "Buffer",
              "data": "Q0zrqYE4lggiGBkQsW3qgsqLC0lTx07OqbSEReNwpIE="
            }
          },
          "7ukliVf7+zRghJcmuTWd1awT8lvQ8vYvDusuMULR24o=": {
            "valueMac": {
              "type": "Buffer",
              "data": "nno8hpaLGCdrk8Z1Hk4XpZhjR2DnbSohshTLmRU5wHI="
            }
          },
          "ruq1w3mr8B/HYogtHGC0I3rzGBAElTV6Q89nwc7M3H8=": {
            "valueMac": {
              "type": "Buffer",
              "data": "3+YK2P+5vaDigpT8deq/HcKJamdgO34em9j3Okfi86M="
            }
          },
          "4TUAnQWeOaWEgdY3F6gcOOA0ErYyBA0UlsTtgi2bUGE=": {
            "valueMac": {
              "type": "Buffer",
              "data": "XWG57yGIlfAaS9zuLx6YgYC5kIYqHVJUMlGr7e2v13U="
            }
          },
          "t4/e20+F0/dWGPj+pcWCn3qOjwGfFFodE88Fkf6mGTE=": {
            "valueMac": {
              "type": "Buffer",
              "data": "xcpP8rN9Yl66n8xlNwOfK66S11rAgdAU71kY+u6lqns="
            }
          },
          "ujRIL1B7GVQWFDPAw0bN89AN6umgh+RINTqxnh1HJ70=": {
            "valueMac": {
              "type": "Buffer",
              "data": "SjKD0MBPH9MebG9iAwHkxQH5nCcEPYz/jJ3m/dkmt38="
            }
          },
          "YLrR9gIkJVGIRW0awPFml+vFhjlFiBIdZ41GqS/oqDw=": {
            "valueMac": {
              "type": "Buffer",
              "data": "dTq7ajPkEWiyClc6gTKoTwp+Skhn+Gpsn6EWVh2Oh78="
            }
          },
          "D38YMIWP4dtXi/3rR554py8ztRc684ze257pi5xFrz8=": {
            "valueMac": {
              "type": "Buffer",
              "data": "PTP6x4R0B9NNoh+AqD7sksJkEAiv6mebjt/w5oUMvA0="
            }
          },
          "+cMZwEMbRRbZnTkXhJ0/mIvYSRejTeLrPI5fH7U2whE=": {
            "valueMac": {
              "type": "Buffer",
              "data": "y0m1IyFfaKq3LkxiWwKig4JipEH1cjJ7CE63uDiLBhA="
            }
          },
          "0QAiEFQpNTMJy1zThSqYIh9pTcrWyYkm1ZNGfl9PWRE=": {
            "valueMac": {
              "type": "Buffer",
              "data": "JfolVeCWqrkJgKTeqjqjvWLFBeSf6/eTmDEwRQxcRSw="
            }
          },
          "5ZM5wlSOcA6gBj3Vlg3R+kxr3tn6oR78A1Sazr86tqk=": {
            "valueMac": {
              "type": "Buffer",
              "data": "thqxuQXskxLes/LHFDNrxNogy8H1geSGDAFhqWkFT2g="
            }
          },
          "XFTyAHmSV6rhW+1azRiR/lWnpda4Qkpkw6dN2PSwHbM=": {
            "valueMac": {
              "type": "Buffer",
              "data": "xmiV/EEqeFaOW9dV3cuB2BlJHGK0RndgSBgA8S5N9uA="
            }
          },
          "isSscRDH/9vgtMs0lmweZ24uxpQ1hFkVSH3VyPGNoRg=": {
            "valueMac": {
              "type": "Buffer",
              "data": "Jq8rJmb9PO2smH+ShdbflMC9w1amioE+i4zEGokG17U="
            }
          },
          "gTm66wKIz6QKhTnHDZXL+6WfsQZKJWlS1GpKy99o8ME=": {
            "valueMac": {
              "type": "Buffer",
              "data": "oVLhRX9oeJmi3JlPEc3qX5Z2m1Q7Dbw9dHa1iQIT/ic="
            }
          },
          "jn36HHhldR2Ex0NkBd2E2xATQKAY7GoU5YulvN+Dk48=": {
            "valueMac": {
              "type": "Buffer",
              "data": "Dp8iYsvE3PB3tJkhQOLykzafKKRkIgBFzY1Rbs39DcY="
            }
          },
          "3iPTbxXSNHxHPdFMWl3OgrZM9qthfe4GZuDaQJKt7ZA=": {
            "valueMac": {
              "type": "Buffer",
              "data": "apl3VEz8xQPdTwojPSiVV0z7rqam2h7qhOWcARTD3ew="
            }
          },
          "aFx1nSu10i7Pq8GNLvq6u5rhJdZiyyQCI2SCK8IEjM4=": {
            "valueMac": {
              "type": "Buffer",
              "data": "lw4gIfI0UQ7BT3KsLx2bGQWxatkQQkG0Ns29Qn0d45M="
            }
          },
          "35gmRd7PFm9RPy25aUd8m3UwBDRqDjN1YqIkRiWCSQM=": {
            "valueMac": {
              "type": "Buffer",
              "data": "wolvFDgQS6CzglS/oQTKkLAwVhTtejjgVad8pzl8mjQ="
            }
          },
          "ga6dSAOrrXOIKRcgvKTLa4jVzI+gF/PrljxF99opK2Y=": {
            "valueMac": {
              "type": "Buffer",
              "data": "yuIuqoUQvotpLTvgF0fanspjQ15v5mZf7eXOYQ+YuWg="
            }
          },
          "a+noWU1HpB0IiRa/+OMKNvbA/5f8KtEbLEbrl19+ZzE=": {
            "valueMac": {
              "type": "Buffer",
              "data": "sHXd3FF4D1joGVMvAFsgDpDJ0zxHIM8+KONBWAn4QXU="
            }
          },
          "s0UxFRGeuVuVNHpH8I1aX3dwe4fRYEii/gPJdRzY71Q=": {
            "valueMac": {
              "type": "Buffer",
              "data": "zdXL1nq9NZmUWUS9rnGQ4mOqAADXXb0Amb/bSCf55qE="
            }
          },
          "fysdoXhtebGkxNjoP0/EMeEOHjFLwaqf+I6GC9+llq8=": {
            "valueMac": {
              "type": "Buffer",
              "data": "roWr1mnmt6AdicZqxeTPIyqf1feFtaKmcvFC3ZDQxm0="
            }
          },
          "H+0sPRaBPPbOYb4LOGYsQBamEfAfd3lrwjAbdp73sWw=": {
            "valueMac": {
              "type": "Buffer",
              "data": "8LHJce/tEKgsWgU9KkFWDdYeW0v+f6pXhvOOXKbQVr0="
            }
          },
          "zMZYr9TtDXRzKkOniGGSmT3VgHT1brJk7tx2gY1GoRQ=": {
            "valueMac": {
              "type": "Buffer",
              "data": "M4VblBQzzHoqkQ//OdsbxN26vmonqW6TRoTVbin5TNY="
            }
          },
          "QaJ6XrlWUNUO18B6V0ZAcYIGVh+F3tvslfdh2rN5m/w=": {
            "valueMac": {
              "type": "Buffer",
              "data": "jPSpqpAJblPHkeWgtDPRb4EmqXsqR+64FGMp7eFYtjA="
            }
          },
          "l5sCbQRSKkx+hpw9jzCzDiOxe7vK/1Dh61ix9etTJrU=": {
            "valueMac": {
              "type": "Buffer",
              "data": "GlahroVztMA9uUwQQkW4VT/Sdo/89EESJGeWZv3Mh3Y="
            }
          },
          "zqAem0fetIQZBYiSILMBqjHR2g6upsPADTzSDV5WxUk=": {
            "valueMac": {
              "type": "Buffer",
              "data": "mz2ya/oCeSMHQpkYO1O+FGe1uCQ1RB+gklHzLw/mb4k="
            }
          },
          "RUbv6LfnzZmQRr9nmmz2gOQDKxf1njbDjEBeSTErIIk=": {
            "valueMac": {
              "type": "Buffer",
              "data": "0ROgyye1qXWpf/k2OlIj2vjpgptUjSWDeyuCmETYcto="
            }
          },
          "Vb9aLC9IuTTheNIAO6adwkm//mDXqMxw4rIERj24obY=": {
            "valueMac": {
              "type": "Buffer",
              "data": "5tAPJHV0L5hY/tUa/ghVT1Is/EyL0iGW++uAQI3CNy8="
            }
          },
          "q/U4Xq32R7pk0zWoo71WdSsbTcngQPvp8muL7FUU5IY=": {
            "valueMac": {
              "type": "Buffer",
              "data": "g2rarhTWhD6Vcqvw0OjM7MtFOJuhcmkOhVxvLzW9sLA="
            }
          },
          "X86walwkxL2LsJk+NbHY+NklwONl9jeq+jrwRDyMz0M=": {
            "valueMac": {
              "type": "Buffer",
              "data": "dN7EriEcMjoGo5vGG6RF4QZUff8iKauhMg4tk4KBzp0="
            }
          },
          "ZKKD01wiFCIHtmyoT6OYCmufKeNAhwt96sPecgcpRhM=": {
            "valueMac": {
              "type": "Buffer",
              "data": "aoyeteDfVru7pKyvEfh4qWHKtfs7ygVfi78WQiyImHg="
            }
          },
          "xK8DwKbKgRvWop3UwNNj6cPLGN+nroWgDq+NMWosQsE=": {
            "valueMac": {
              "type": "Buffer",
              "data": "7xktjTUYRD44PhEIWiS7uOUBNKplewqIyi1rzo2W+4M="
            }
          },
          "Z+Mxe5PCV9l10Ruy5TqSvQmTShV8/dz0TP/NJ7JROgo=": {
            "valueMac": {
              "type": "Buffer",
              "data": "lMdnnA3FIu0pIQeqAQzRgy6cG3tfm3i7ZQZR+bun4CQ="
            }
          },
          "3oRssikUc1X327xaUCBN9Zk5I+hZ2yMatz4SEYqaEVA=": {
            "valueMac": {
              "type": "Buffer",
              "data": "VmfE5cYCJQeUPVmCDEg/zInombDR5P0Wqp4RhU03p8M="
            }
          },
          "JqkibRCXmgpx5szKeo4xusqqOoCR+PUjQXQmITmz+h4=": {
            "valueMac": {
              "type": "Buffer",
              "data": "AyuAyH9mlp95Yd9CEUV+bEF4daswQIwU0ofi182k6hE="
            }
          }
        }
      },
      "regular_high": {
        "version": 1,
        "hash": {
          "type": "Buffer",
          "data": "TmFmAa08/WxXapvnWGeDA7hVF2uGBcM7OipKkFw30lFTS7pQhv0qVeN072BmvTfvyy0+yReqleGf1KkkC5J8iw0eP90/txICLweBmJS/v5glAS6qLRbdqHMwlDpP9JB0E6avjeSRymqnOdjVgOVUuM0t3Ppapn8hOPvFk2MTXkU="
        },
        "indexValueMap": {
          "D5hM/RyHYyP7ryzF0oKWRLtyHJ5nZLtDKU4f1bCaIxY=": {
            "valueMac": {
              "type": "Buffer",
              "data": "E2/xYjnVL6mCSoInp8iJcwCCKdTEbNuhwANunjsOS30="
            }
          }
        }
      },
      "regular_low": {
        "version": 1,
        "hash": {
          "type": "Buffer",
          "data": "KxuQmt9GcTt7D6mgt08UErXrpFE3uuNw5Y0DoNi4rhC/tMVBZdgIap0fagpnJKMhP3miwp5F5sZwrXaqH37/GlU0IvjOnIqpmerj/J0/eofR8SbLf8VudMZXji9Ewef7HzpBiu0t5debr6901i4KARy00cWypWpGMmJrXE8hb+I="
        },
        "indexValueMap": {
          "HRCnE3WeOaFodKL3Iyq9kwHKz8ZLoiQu8LubupL9yRE=": {
            "valueMac": {
              "type": "Buffer",
              "data": "IsPRJ7k6lqAqcjCSO2h5sHO6Q45KlgaS4jhKBEx0Jbc="
            }
          },
          "YAKzHjEvoUL12k08JwzZiuyJhuDTVRQ653kYtCdtSEk=": {
            "valueMac": {
              "type": "Buffer",
              "data": "AJkK5kIgEPyq35+5h40QZDBAInRvIojjYXvsrwRtIlQ="
            }
          },
          "e00DbCfE0ndkpcHhq9/bFR0yT3AededB6EpELRbMoO8=": {
            "valueMac": {
              "type": "Buffer",
              "data": "Poz1mFAVLdFEvxm3xuMwKwlUJHNmku4zJA9AYUzUCuA="
            }
          },
          "uN/OqNePrSdcT7XPmAYq/E1JOqEBflOdxIz6Y6MZ+hw=": {
            "valueMac": {
              "type": "Buffer",
              "data": "jGRCp8Ho/0WtUnbMmi+PvmELKLF5VU9MEUBwPTbaXJk="
            }
          },
          "4yiE4z8x0NanfmHa+NiVnf7K6fQmdFMaLCNLi1hHa/g=": {
            "valueMac": {
              "type": "Buffer",
              "data": "luKI+Km0Ad79EaWbRdMvzDl5P7ZqEB9qqEsWzQFmzDE="
            }
          },
          "y78E+VWEl5OgNbdQvw8yFdy/2FOCbLBRx1nOHNdAqLE=": {
            "valueMac": {
              "type": "Buffer",
              "data": "FRz6V5Xb6pB0/Ge9rvFwDcFwfdGm41PtbqQ8cs++8kk="
            }
          }
        }
      }
    },
    "senderKeys": {
      "120363040631151706@g.us::6281996224181::0": [
        {
          "senderKeyId": 161199275,
          "senderChainKey": {
            "iteration": 2,
            "seed": "fuFQNOoFjomWJjEEFdGzmjxgLbHnqjfvH8LLpCX5Mvw="
          },
          "senderSigningKey": {
            "public": "BQ7D3rsbcOKAhh5QfWwmYGMqYBr+kEsuf8jriVoMUiND"
          }
        }
      ],
      "120363040631151706@g.us::62859106985947:3::0": [
        {
          "senderKeyId": 5230516,
          "senderChainKey": {
            "iteration": 1,
            "seed": "vaEGuxMs+wn2H3joo+Y5oGIX/m2nxfk0HXBoN/TeeTI="
          },
          "senderSigningKey": {
            "public": "BbYB9Kw+gFXHQ0hDplFos0K/Ke6Lwt5wWMSOHveZiysd"
          }
        }
      ],
      "120363040631151706@g.us::6281221719733::0": [
        {
          "senderKeyId": 2049111757,
          "senderChainKey": {
            "iteration": 5,
            "seed": "VLzYAS6JCMbVVM2bYwdQJ1qPaDSpfza+w7ZaNG5c/t8="
          },
          "senderSigningKey": {
            "public": "BfR6FMZYz+meBynSonrAmW6hB//8fG1uK8zPxjWLJDYy"
          }
        }
      ],
      "120363040631151706@g.us::6285722029127::0": [
        {
          "senderKeyId": 1703529307,
          "senderChainKey": {
            "iteration": 20,
            "seed": "1pa3K4unni5DE07EunDPntkhDlk+/FTH2Jk5TiewKkk="
          },
          "senderSigningKey": {
            "public": "BYQvsXgeb5QF58tFzt5dX4+EQJ4sDm5dCirAW6FGYWpw"
          }
        }
      ]
    }
  }
}